ooflow/__init__.py
ooflow/ooflow.py
ooflow-0.1.2.dist-info/licenses/LICENSE
ooflow-0.1.2.dist-info/METADATA
ooflow-0.1.2.dist-info/WHEEL
ooflow-0.1.2.dist-info/top_level.txt
ooflow-0.1.2.dist-info/RECORD
