Metadata-Version: 2.4
Name: ooflow
Version: 0.1.2
Summary: A lightweight Python framework for building asynchronous data processing pipelines with stateful nodes
Home-page: https://github.com/fanfank/ooflow
Author: fanfank
Author-email: fanfank <fanfank@example.com>
License: MIT
Project-URL: Homepage, https://github.com/fanfank/ooflow
Project-URL: Bug Reports, https://github.com/fanfank/ooflow/issues
Project-URL: Source Code, https://github.com/fanfank/ooflow
Project-URL: Documentation, https://github.com/fanfank/ooflow#readme
Keywords: async,stateful,ai,streaming,asyncio,graph,nodes,pipeline,workflow,data-processing
Classifier: Development Status :: 4 - Beta
Classifier: Intended Audience :: Developers
Classifier: License :: OSI Approved :: MIT License
Classifier: Operating System :: OS Independent
Classifier: Programming Language :: Python :: 3
Classifier: Programming Language :: Python :: 3.9
Classifier: Programming Language :: Python :: 3.10
Classifier: Programming Language :: Python :: 3.11
Classifier: Programming Language :: Python :: 3.12
Classifier: Topic :: Software Development :: Libraries :: Python Modules
Classifier: Topic :: System :: Distributed Computing
Classifier: Topic :: Software Development :: Libraries :: Application Frameworks
Requires-Python: >=3.9
License-File: LICENSE
Requires-Dist: typing_extensions>=4.0.0; python_version < "3.10"
Provides-Extra: dev
Requires-Dist: pytest>=6.0; extra == "dev"
Requires-Dist: pytest-asyncio>=0.18.0; extra == "dev"
Requires-Dist: coverage>=5.0; extra == "dev"
Requires-Dist: black>=21.0; extra == "dev"
Requires-Dist: flake8>=3.8; extra == "dev"
Requires-Dist: mypy>=0.800; extra == "dev"
Provides-Extra: test
Requires-Dist: pytest>=6.0; extra == "test"
Requires-Dist: pytest-asyncio>=0.18.0; extra == "test"
Requires-Dist: coverage>=5.0; extra == "test"
Dynamic: author
Dynamic: home-page
Dynamic: license-file
Dynamic: requires-python
